motile/__init__.py
motile/_types.py
motile/solver.py
motile/ssvm.py
motile/track_graph.py
motile/constraints/__init__.py
motile/constraints/constraint.py
motile/constraints/exclusive_nodes.py
motile/constraints/expression.py
motile/constraints/max_children.py
motile/constraints/max_parents.py
motile/constraints/pin.py
motile/costs/__init__.py
motile/costs/appear.py
motile/costs/cost.py
motile/costs/disappear.py
motile/costs/edge_distance.py
motile/costs/edge_selection.py
motile/costs/features.py
motile/costs/node_selection.py
motile/costs/split.py
motile/costs/weight.py
motile/costs/weights.py
motile/variables/__init__.py
motile/variables/edge_selected.py
motile/variables/node_appear.py
motile/variables/node_disappear.py
motile/variables/node_selected.py
motile/variables/node_split.py
motile/variables/variable.py
motile-0.3.0.dist-info/METADATA
motile-0.3.0.dist-info/WHEEL
motile-0.3.0.dist-info/licenses/LICENSE
motile-0.3.0.dist-info/RECORD
