Metadata-Version: 2.3
Name: motile
Version: 0.3.0
Summary: Multi-Object Tracker using Integer Linear Equations
Project-URL: homepage, https://github.com/funkelab/motile
Author-email: Jan Funke <funkej@janelia.hhmi.org>, Talley Lambert <talley.lambert@gmail.com>, Caroline Malin-Mayor <malinmayorc@janelia.hhmi.org>, Benjamin Gallusser <bgallusser@googlemail.com>, Florian Jug <florian.jug@fht.org>
License: MIT
License-File: LICENSE
Requires-Dist: ilpy>=0.4.0
Requires-Dist: networkx
Requires-Dist: numpy
Requires-Dist: structsvm
Provides-Extra: dev
Requires-Dist: build; extra == 'dev'
Requires-Dist: pre-commit; extra == 'dev'
Requires-Dist: pytest; extra == 'dev'
Requires-Dist: pytest-cov; extra == 'dev'
Requires-Dist: ruff; extra == 'dev'
Requires-Dist: twine; extra == 'dev'
Provides-Extra: docs
Requires-Dist: ipykernel; extra == 'docs'
Requires-Dist: jupyter-sphinx; extra == 'docs'
Requires-Dist: motile-toolbox; extra == 'docs'
Requires-Dist: sphinx; extra == 'docs'
Requires-Dist: sphinx-autodoc-typehints; extra == 'docs'
Requires-Dist: sphinx-rtd-theme; extra == 'docs'
Requires-Dist: sphinx-togglebutton; extra == 'docs'
Requires-Dist: tomli; extra == 'docs'
Provides-Extra: test
Requires-Dist: pytest; extra == 'test'
Requires-Dist: pytest-cov; extra == 'test'
